QBinder/__init__.py
QBinder/binder.py
QBinder/binding.py
QBinder/constant.py
QBinder/decorator.py
QBinder/eventhook.py
QBinder/handler.py
QBinder/hook.py
QBinder/hookconfig.py
QBinder/mixin.py
QBinder/panel/__init__.py
QBinder/panel/panel.py
QBinder/util/__init__.py
QBinder/util/collapsible.py
QBinder/util/listget.py
QBinder-1.0.10.dist-info/METADATA
QBinder-1.0.10.dist-info/WHEEL
QBinder-1.0.10.dist-info/top_level.txt
QBinder-1.0.10.dist-info/RECORD
