Metadata-Version: 2.1
Name: QBinder
Version: 1.0.10
Summary: Global Data Binding for Python Qt framework
Home-page: https://github.com/FXTD-ODYSSEY/QBinder
Author: timmyliang
Author-email: 820472580@qq.com
License: MIT Licence
Keywords: pip,PyQt,PySide,Qt,DataBinding,Binding,Binder
Platform: any
Requires-Dist: PySide2
Requires-Dist: six
Requires-Dist: Qt.py
